Workbook

Sheet Inventário
A1: Origem | B1: Item | C1: Qtd. | D1: Valor real (gp) | E1: Valor estimado (gp) | F1: Como foi estimado | G1: Categoria | H1: Vender? | I1: Valor base (gp) | J1: Bônus aplicado | K1: Venda líquida (gp) | L1: Observação
A2: Goblin — primeira sala | B2: Cimitarra | C2: 1 | E2: 25 | F2: Preço de lista D&D 5e | G2: Item comum | H2: Sim | I2: =IF(D2<>"",D2,IF(E2<>"",E2,0)) -> 25 | J2: =IF(G2="Joia",Parametros!$B$3,IF(G2="Mágico",Parametros!$B$4,Parametros!$B$2)) -> 0.15 | K2: =IF(H2="Sim",I2*(1+J2),0) -> 28.75
A3: Goblin — primeira sala | B3: Escudo | C3: 1 | E3: 10 | F3: Preço de lista D&D 5e | G3: Item comum | H3: Sim | I3: =IF(D3<>"",D3,IF(E3<>"",E3,0)) -> 10 | J3: =IF(G3="Joia",Parametros!$B$3,IF(G3="Mágico",Parametros!$B$4,Parametros!$B$2)) -> 0.15 | K3: =IF(H3="Sim",I3*(1+J3),0) -> 11.5
A4: Humanos — sala escondida 2 | B4: Moedas: 43 pp | C4: 1 | D4: 4.3 | F4: 43 pp × 0,1 gp | G4: Moedas | H4: Não | I4: =IF(D4<>"",D4,IF(E4<>"",E4,0)) -> 4.3 | J4: =IF(G4="Joia",Parametros!$B$3,IF(G4="Mágico",Parametros!$B$4,Parametros!$B$2)) -> 0.15 | K4: =IF(H4="Sim",I4*(1+J4),0) -> 0
A5: Humanos — sala escondida 2 | B5: Moedas: 9 gp | C5: 1 | D5: 9 | F5: Valor anotado | G5: Moedas | H5: Não | I5: =IF(D5<>"",D5,IF(E5<>"",E5,0)) -> 9 | J5: =IF(G5="Joia",Parametros!$B$3,IF(G5="Mágico",Parametros!$B$4,Parametros!$B$2)) -> 0.15 | K5: =IF(H5="Sim",I5*(1+J5),0) -> 0
A6: Humanos — sala escondida 2 | B6: 3 Dardos elementais de uso único | C6: 1 | E6: 150 | F6: Estimativa conservadora: 50 gp cada por efeito mágico de uso único | G6: Mágico | H6: Não | I6: =IF(D6<>"",D6,IF(E6<>"",E6,0)) -> 150 | J6: =IF(G6="Joia",Parametros!$B$3,IF(G6="Mágico",Parametros!$B$4,Parametros!$B$2)) -> 0.15 | K6: =IF(H6="Sim",I6*(1+J6),0) -> 0 | L6: Manter com o grupo / confirmar antes de vender.
A7: Dragão | B7: Escama de wyrmling gelada | C7: 1 | E7: 25 | F7: Componente/curiosidade; estimativa conservadora | G7: Especial | H7: Não | I7: =IF(D7<>"",D7,IF(E7<>"",E7,0)) -> 25 | J7: =IF(G7="Joia",Parametros!$B$3,IF(G7="Mágico",Parametros!$B$4,Parametros!$B$2)) -> 0.15 | K7: =IF(H7="Sim",I7*(1+J7),0) -> 0 | L7: Manter com o grupo / confirmar antes de vender.
A8: Kobolds | B8: Concha gigante | C8: 1 | E8: 5 | F8: Curiosidade decorativa; estimativa | G8: Item comum | H8: Não | I8: =IF(D8<>"",D8,IF(E8<>"",E8,0)) -> 5 | J8: =IF(G8="Joia",Parametros!$B$3,IF(G8="Mágico",Parametros!$B$4,Parametros!$B$2)) -> 0.15 | K8: =IF(H8="Sim",I8*(1+J8),0) -> 0
A9: Kobolds | B9: Material para criar crossbow | C9: 1 | E9: 12.5 | F9: Metade do preço de uma light crossbow (25 gp) | G9: Item comum | H9: Não | I9: =IF(D9<>"",D9,IF(E9<>"",E9,0)) -> 12.5 | J9: =IF(G9="Joia",Parametros!$B$3,IF(G9="Mágico",Parametros!$B$4,Parametros!$B$2)) -> 0.15 | K9: =IF(H9="Sim",I9*(1+J9),0) -> 0
A10: Kobolds | B10: Ferro útil (4 kg / 8 lb) | C10: 1 | E10: 0.8 | F10: Ferro bruto estimado: 0,1 gp/lb | G10: Item comum | H10: Sim | I10: =IF(D10<>"",D10,IF(E10<>"",E10,0)) -> 0.8 | J10: =IF(G10="Joia",Parametros!$B$3,IF(G10="Mágico",Parametros!$B$4,Parametros!$B$2)) -> 0.15 | K10: =IF(H10="Sim",I10*(1+J10),0) -> 0.92
A11: Esqueletos | B11: Apito Nightcaller | C11: 1 | E11: 500 | F11: Item mágico raro; valor de referência muito incerto | G11: Mágico | H11: Não | I11: =IF(D11<>"",D11,IF(E11<>"",E11,0)) -> 500 | J11: =IF(G11="Joia",Parametros!$B$3,IF(G11="Mágico",Parametros!$B$4,Parametros!$B$2)) -> 0.15 | K11: =IF(H11="Sim",I11*(1+J11),0) -> 0 | L11: Manter com o grupo / confirmar antes de vender.
A12: Esqueletos | B12: Poção de resistência a fogo | C12: 1 | E12: 300 | F12: Poção mágica incomum; estimativa | G12: Mágico | H12: Não | I12: =IF(D12<>"",D12,IF(E12<>"",E12,0)) -> 300 | J12: =IF(G12="Joia",Parametros!$B$3,IF(G12="Mágico",Parametros!$B$4,Parametros!$B$2)) -> 0.15 | K12: =IF(H12="Sim",I12*(1+J12),0) -> 0 | L12: Manter com o grupo / confirmar antes de vender.
A13: Esqueletos | B13: Poção de sopro de fogo | C13: 1 | E13: 150 | F13: Poção mágica incomum; estimativa | G13: Mágico | H13: Não | I13: =IF(D13<>"",D13,IF(E13<>"",E13,0)) -> 150 | J13: =IF(G13="Joia",Parametros!$B$3,IF(G13="Mágico",Parametros!$B$4,Parametros!$B$2)) -> 0.15 | K13: =IF(H13="Sim",I13*(1+J13),0) -> 0 | L13: Manter com o grupo / confirmar antes de vender.
A14: Esqueletos | B14: Vela | C14: 1 | E14: 0.01 | F14: Preço de lista D&D 5e | G14: Item comum | H14: Sim | I14: =IF(D14<>"",D14,IF(E14<>"",E14,0)) -> 0.01 | J14: =IF(G14="Joia",Parametros!$B$3,IF(G14="Mágico",Parametros!$B$4,Parametros!$B$2)) -> 0.15 | K14: =IF(H14="Sim",I14*(1+J14),0) -> 0.0115
A15: Esqueletos | B15: 9 pequenas estátuas de dragão em jade | C15: 1 | E15: 90 | F15: Estimativa: 10 gp cada; confirmar avaliação | G15: Joia | H15: Sim | I15: =IF(D15<>"",D15,IF(E15<>"",E15,0)) -> 90 | J15: =IF(G15="Joia",Parametros!$B$3,IF(G15="Mágico",Parametros!$B$4,Parametros!$B$2)) -> 0.05 | K15: =IF(H15="Sim",I15*(1+J15),0) -> 94.5
A16: Ratão | B16: Moedas: 312 pp | C16: 1 | D16: 31.2 | F16: 312 pp × 0,1 gp | G16: Moedas | H16: Não | I16: =IF(D16<>"",D16,IF(E16<>"",E16,0)) -> 31.2 | J16: =IF(G16="Joia",Parametros!$B$3,IF(G16="Mágico",Parametros!$B$4,Parametros!$B$2)) -> 0.15 | K16: =IF(H16="Sim",I16*(1+J16),0) -> 0
A17: Ratão | B17: Moedas: 68 gp | C17: 1 | D17: 68 | F17: Valor anotado | G17: Moedas | H17: Não | I17: =IF(D17<>"",D17,IF(E17<>"",E17,0)) -> 68 | J17: =IF(G17="Joia",Parametros!$B$3,IF(G17="Mágico",Parametros!$B$4,Parametros!$B$2)) -> 0.15 | K17: =IF(H17="Sim",I17*(1+J17),0) -> 0
A18: Ratão | B18: Pepita de ouro | C18: 1 | D18: 17 | F18: Valor anotado | G18: Moedas | H18: Não | I18: =IF(D18<>"",D18,IF(E18<>"",E18,0)) -> 17 | J18: =IF(G18="Joia",Parametros!$B$3,IF(G18="Mágico",Parametros!$B$4,Parametros!$B$2)) -> 0.15 | K18: =IF(H18="Sim",I18*(1+J18),0) -> 0
A19: Ratão | B19: Anel dourado de Karakas | C19: 1 | E19: 25 | F19: Joia simples; mas pertence ao ranger Karakas | G19: Item de missão | H19: Não | I19: =IF(D19<>"",D19,IF(E19<>"",E19,0)) -> 25 | J19: =IF(G19="Joia",Parametros!$B$3,IF(G19="Mágico",Parametros!$B$4,Parametros!$B$2)) -> 0.15 | K19: =IF(H19="Sim",I19*(1+J19),0) -> 0 | L19: Manter com o grupo / confirmar antes de vender.
A20: Ratão | B20: 2 Adagas | C20: 1 | E20: 4 | F20: 2 × 2 gp (preço de lista) | G20: Item comum | H20: Sim | I20: =IF(D20<>"",D20,IF(E20<>"",E20,0)) -> 4 | J20: =IF(G20="Joia",Parametros!$B$3,IF(G20="Mágico",Parametros!$B$4,Parametros!$B$2)) -> 0.15 | K20: =IF(H20="Sim",I20*(1+J20),0) -> 4.6
A21: Ratão | B21: Arco longo | C21: 1 | E21: 50 | F21: Preço de lista D&D 5e | G21: Item comum | H21: Sim | I21: =IF(D21<>"",D21,IF(E21<>"",E21,0)) -> 50 | J21: =IF(G21="Joia",Parametros!$B$3,IF(G21="Mágico",Parametros!$B$4,Parametros!$B$2)) -> 0.15 | K21: =IF(H21="Sim",I21*(1+J21),0) -> 57.5
A22: Ratão | B22: Aljava | C22: 1 | E22: 1 | F22: Preço de lista D&D 5e | G22: Item comum | H22: Sim | I22: =IF(D22<>"",D22,IF(E22<>"",E22,0)) -> 1 | J22: =IF(G22="Joia",Parametros!$B$3,IF(G22="Mágico",Parametros!$B$4,Parametros!$B$2)) -> 0.15 | K22: =IF(H22="Sim",I22*(1+J22),0) -> 1.15
A23: Ratão | B23: 3 gemas | C23: 1 | D23: 75 | F23: 3 × 25 gp anotados | G23: Joia | H23: Sim | I23: =IF(D23<>"",D23,IF(E23<>"",E23,0)) -> 75 | J23: =IF(G23="Joia",Parametros!$B$3,IF(G23="Mágico",Parametros!$B$4,Parametros!$B$2)) -> 0.05 | K23: =IF(H23="Sim",I23*(1+J23),0) -> 78.75
A24: Ratão | B24: Waterskin, comida, bedroll, fósforos e 3 tochas | C24: 1 | E24: 4 | F24: Estimativa por equipamento básico; confirmar conteúdo | G24: Item comum | H24: Não | I24: =IF(D24<>"",D24,IF(E24<>"",E24,0)) -> 4 | J24: =IF(G24="Joia",Parametros!$B$3,IF(G24="Mágico",Parametros!$B$4,Parametros!$B$2)) -> 0.15 | K24: =IF(H24="Sim",I24*(1+J24),0) -> 0
A25: Ratão | B25: Concha pequena | C25: 1 | E25: 0.5 | F25: Curiosidade decorativa; estimativa | G25: Item comum | H25: Não | I25: =IF(D25<>"",D25,IF(E25<>"",E25,0)) -> 0.5 | J25: =IF(G25="Joia",Parametros!$B$3,IF(G25="Mágico",Parametros!$B$4,Parametros!$B$2)) -> 0.15 | K25: =IF(H25="Sim",I25*(1+J25),0) -> 0
A26: Goblins mortos / goblin cativo | B26: Moedas: 50 gp | C26: 1 | D26: 50 | F26: Valor anotado | G26: Moedas | H26: Não | I26: =IF(D26<>"",D26,IF(E26<>"",E26,0)) -> 50 | J26: =IF(G26="Joia",Parametros!$B$3,IF(G26="Mágico",Parametros!$B$4,Parametros!$B$2)) -> 0.15 | K26: =IF(H26="Sim",I26*(1+J26),0) -> 0
A27: Goblins mortos / goblin cativo | B27: Cimitarra | C27: 1 | E27: 25 | F27: Preço de lista D&D 5e | G27: Item comum | H27: Sim | I27: =IF(D27<>"",D27,IF(E27<>"",E27,0)) -> 25 | J27: =IF(G27="Joia",Parametros!$B$3,IF(G27="Mágico",Parametros!$B$4,Parametros!$B$2)) -> 0.15 | K27: =IF(H27="Sim",I27*(1+J27),0) -> 28.75
A28: Goblins mortos / goblin cativo | B28: Arco curto | C28: 1 | E28: 25 | F28: Preço de lista D&D 5e | G28: Item comum | H28: Sim | I28: =IF(D28<>"",D28,IF(E28<>"",E28,0)) -> 25 | J28: =IF(G28="Joia",Parametros!$B$3,IF(G28="Mágico",Parametros!$B$4,Parametros!$B$2)) -> 0.15 | K28: =IF(H28="Sim",I28*(1+J28),0) -> 28.75
A29: Goblins mortos / goblin cativo | B29: Chave | C29: 1 | E29: 0 | F29: Chave de dungeon; sem venda até confirmar uso | G29: Item de missão | H29: Sim | I29: =IF(D29<>"",D29,IF(E29<>"",E29,0)) -> 0 | J29: =IF(G29="Joia",Parametros!$B$3,IF(G29="Mágico",Parametros!$B$4,Parametros!$B$2)) -> 0.15 | K29: =IF(H29="Sim",I29*(1+J29),0) -> 0 | L29: Manter com o grupo / confirmar antes de vender.
A30: Goblins mortos / goblin cativo | B30: Frasco prateado de Durgeddin com vinho goblin | C30: 1 | D30: 50 | F30: Valor anotado | G30: Arte | H30: Sim | I30: =IF(D30<>"",D30,IF(E30<>"",E30,0)) -> 50 | J30: =IF(G30="Joia",Parametros!$B$3,IF(G30="Mágico",Parametros!$B$4,Parametros!$B$2)) -> 0.15 | K30: =IF(H30="Sim",I30*(1+J30),0) -> 57.5
A31: Goblins mortos / goblin cativo | B31: 9 arcos curtos | C31: 1 | E31: 225 | F31: 9 × 25 gp (preço de lista) | G31: Item comum | H31: Sim | I31: =IF(D31<>"",D31,IF(E31<>"",E31,0)) -> 225 | J31: =IF(G31="Joia",Parametros!$B$3,IF(G31="Mágico",Parametros!$B$4,Parametros!$B$2)) -> 0.15 | K31: =IF(H31="Sim",I31*(1+J31),0) -> 258.75
A32: Goblins mortos / goblin cativo | B32: 2 cimitarras | C32: 1 | E32: 50 | F32: 2 × 25 gp (preço de lista) | G32: Item comum | H32: Sim | I32: =IF(D32<>"",D32,IF(E32<>"",E32,0)) -> 50 | J32: =IF(G32="Joia",Parametros!$B$3,IF(G32="Mágico",Parametros!$B$4,Parametros!$B$2)) -> 0.15 | K32: =IF(H32="Sim",I32*(1+J32),0) -> 57.5
A33: Sala ao lado dos goblins mortos | B33: 5 frascos de óleo | C33: 1 | E33: 0.5 | F33: 5 × 0,1 gp (preço de lista) | G33: Item comum | H33: Não | I33: =IF(D33<>"",D33,IF(E33<>"",E33,0)) -> 0.5 | J33: =IF(G33="Joia",Parametros!$B$3,IF(G33="Mágico",Parametros!$B$4,Parametros!$B$2)) -> 0.15 | K33: =IF(H33="Sim",I33*(1+J33),0) -> 0
A34: Sala ao lado dos goblins mortos | B34: Caracol vivo | C34: 1 | E34: 1 | F34: Animal/curiosidade; estimativa | G34: Especial | H34: Não | I34: =IF(D34<>"",D34,IF(E34<>"",E34,0)) -> 1 | J34: =IF(G34="Joia",Parametros!$B$3,IF(G34="Mágico",Parametros!$B$4,Parametros!$B$2)) -> 0.15 | K34: =IF(H34="Sim",I34*(1+J34),0) -> 0 | L34: Manter com o grupo / confirmar antes de vender.
A35: Goblins do topo | B35: 2 cimitarras | C35: 1 | E35: 50 | F35: 2 × 25 gp (preço de lista) | G35: Item comum | H35: Sim | I35: =IF(D35<>"",D35,IF(E35<>"",E35,0)) -> 50 | J35: =IF(G35="Joia",Parametros!$B$3,IF(G35="Mágico",Parametros!$B$4,Parametros!$B$2)) -> 0.15 | K35: =IF(H35="Sim",I35*(1+J35),0) -> 57.5
A36: Goblins do topo | B36: 3 arcos curtos | C36: 1 | E36: 75 | F36: 3 × 25 gp (preço de lista) | G36: Item comum | H36: Sim | I36: =IF(D36<>"",D36,IF(E36<>"",E36,0)) -> 75 | J36: =IF(G36="Joia",Parametros!$B$3,IF(G36="Mágico",Parametros!$B$4,Parametros!$B$2)) -> 0.15 | K36: =IF(H36="Sim",I36*(1+J36),0) -> 86.25
A37: Goblins do topo | B37: Concha de caracol bonita | C37: 1 | E37: 1 | F37: Curiosidade decorativa; estimativa | G37: Item comum | H37: Não | I37: =IF(D37<>"",D37,IF(E37<>"",E37,0)) -> 1 | J37: =IF(G37="Joia",Parametros!$B$3,IF(G37="Mágico",Parametros!$B$4,Parametros!$B$2)) -> 0.15 | K37: =IF(H37="Sim",I37*(1+J37),0) -> 0
A38: Caltrix | B38: Estátua de dragão em jade | C38: 1 | D38: 20 | F38: Valor anotado | G38: Joia | H38: Sim | I38: =IF(D38<>"",D38,IF(E38<>"",E38,0)) -> 20 | J38: =IF(G38="Joia",Parametros!$B$3,IF(G38="Mágico",Parametros!$B$4,Parametros!$B$2)) -> 0.05 | K38: =IF(H38="Sim",I38*(1+J38),0) -> 21
A39: Caltrix | B39: Cálice de cristal | C39: 1 | D39: 5 | F39: Valor anotado | G39: Arte | H39: Sim | I39: =IF(D39<>"",D39,IF(E39<>"",E39,0)) -> 5 | J39: =IF(G39="Joia",Parametros!$B$3,IF(G39="Mágico",Parametros!$B$4,Parametros!$B$2)) -> 0.15 | K39: =IF(H39="Sim",I39*(1+J39),0) -> 5.75
A40: Caltrix | B40: 24 peças de prataria | C40: 1 | D40: 24 | F40: 24 × 1 gp anotado | G40: Arte | H40: Sim | I40: =IF(D40<>"",D40,IF(E40<>"",E40,0)) -> 24 | J40: =IF(G40="Joia",Parametros!$B$3,IF(G40="Mágico",Parametros!$B$4,Parametros!$B$2)) -> 0.15 | K40: =IF(H40="Sim",I40*(1+J40),0) -> 27.6
A41: Caltrix | B41: Case de scroll com runas anãs e papiro | C41: 1 | E41: 5 | F41: Objeto histórico; estimativa baixa (papiro incompleto) | G41: Lore | H41: Não | I41: =IF(D41<>"",D41,IF(E41<>"",E41,0)) -> 5 | J41: =IF(G41="Joia",Parametros!$B$3,IF(G41="Mágico",Parametros!$B$4,Parametros!$B$2)) -> 0.15 | K41: =IF(H41="Sim",I41*(1+J41),0) -> 0 | L41: Manter com o grupo / confirmar antes de vender.
A42: Kobold Rainha | B42: Chave mágica | C42: 1 | E42: 50 | F42: Valor incerto; pode abrir área relevante | G42: Mágico | H42: Sim | I42: =IF(D42<>"",D42,IF(E42<>"",E42,0)) -> 50 | J42: =IF(G42="Joia",Parametros!$B$3,IF(G42="Mágico",Parametros!$B$4,Parametros!$B$2)) -> 0.15 | K42: =IF(H42="Sim",I42*(1+J42),0) -> 57.5 | L42: Manter com o grupo / confirmar antes de vender.
A43: Kobold Rainha | B43: Quaal's Feather Token (Tree) | C43: 1 | E43: 500 | F43: Item mágico incomum; estimativa de referência | G43: Mágico | H43: Não | I43: =IF(D43<>"",D43,IF(E43<>"",E43,0)) -> 500 | J43: =IF(G43="Joia",Parametros!$B$3,IF(G43="Mágico",Parametros!$B$4,Parametros!$B$2)) -> 0.15 | K43: =IF(H43="Sim",I43*(1+J43),0) -> 0 | L43: Manter com o grupo / confirmar antes de vender.
A44: Kobold Rainha | B44: Scroll: Mage Armor | C44: 1 | E44: 50 | F44: Pergaminho mágico nível 1; estimativa | G44: Mágico | H44: Não | I44: =IF(D44<>"",D44,IF(E44<>"",E44,0)) -> 50 | J44: =IF(G44="Joia",Parametros!$B$3,IF(G44="Mágico",Parametros!$B$4,Parametros!$B$2)) -> 0.15 | K44: =IF(H44="Sim",I44*(1+J44),0) -> 0 | L44: Manter com o grupo / confirmar antes de vender.
A45: Kobold Rainha | B45: Scroll: Spider Climb | C45: 1 | E45: 50 | F45: Pergaminho mágico nível 2; estimativa | G45: Mágico | H45: Não | I45: =IF(D45<>"",D45,IF(E45<>"",E45,0)) -> 50 | J45: =IF(G45="Joia",Parametros!$B$3,IF(G45="Mágico",Parametros!$B$4,Parametros!$B$2)) -> 0.15 | K45: =IF(H45="Sim",I45*(1+J45),0) -> 0 | L45: Manter com o grupo / confirmar antes de vender.
A46: Kobold Rainha | B46: Scroll: Knock | C46: 1 | E46: 50 | F46: Pergaminho mágico nível 2; estimativa | G46: Mágico | H46: Não | I46: =IF(D46<>"",D46,IF(E46<>"",E46,0)) -> 50 | J46: =IF(G46="Joia",Parametros!$B$3,IF(G46="Mágico",Parametros!$B$4,Parametros!$B$2)) -> 0.15 | K46: =IF(H46="Sim",I46*(1+J46),0) -> 0 | L46: Manter com o grupo / confirmar antes de vender.
A47: Kobold Rainha | B47: Elixir of Health (3 doses) | C47: 1 | E47: 600 | F47: Estimativa: 200 gp por dose; confirmar mesa | G47: Mágico | H47: Não | I47: =IF(D47<>"",D47,IF(E47<>"",E47,0)) -> 600 | J47: =IF(G47="Joia",Parametros!$B$3,IF(G47="Mágico",Parametros!$B$4,Parametros!$B$2)) -> 0.15 | K47: =IF(H47="Sim",I47*(1+J47),0) -> 0 | L47: Manter com o grupo / confirmar antes de vender.
A48: Kobold Rainha — baú | B48: Moedas: 35 gp | C48: 1 | D48: 35 | F48: Valor anotado | G48: Moedas | H48: Não | I48: =IF(D48<>"",D48,IF(E48<>"",E48,0)) -> 35 | J48: =IF(G48="Joia",Parametros!$B$3,IF(G48="Mágico",Parametros!$B$4,Parametros!$B$2)) -> 0.15 | K48: =IF(H48="Sim",I48*(1+J48),0) -> 0
A49: Troll | B49: Moedas: 220 pp | C49: 1 | D49: 22 | F49: 220 pp × 0,1 gp | G49: Moedas | H49: Não | I49: =IF(D49<>"",D49,IF(E49<>"",E49,0)) -> 22 | J49: =IF(G49="Joia",Parametros!$B$3,IF(G49="Mágico",Parametros!$B$4,Parametros!$B$2)) -> 0.15 | K49: =IF(H49="Sim",I49*(1+J49),0) -> 0
A50: Troll | B50: Moedas: 50 gp | C50: 1 | D50: 50 | F50: Valor anotado | G50: Moedas | H50: Não | I50: =IF(D50<>"",D50,IF(E50<>"",E50,0)) -> 50 | J50: =IF(G50="Joia",Parametros!$B$3,IF(G50="Mágico",Parametros!$B$4,Parametros!$B$2)) -> 0.15 | K50: =IF(H50="Sim",I50*(1+J50),0) -> 0
A51: Troll | B51: Adaga com runas élficas/dracônicas | C51: 1 | D51: 125 | F51: Valor anotado | G51: Especial | H51: Não | I51: =IF(D51<>"",D51,IF(E51<>"",E51,0)) -> 125 | J51: =IF(G51="Joia",Parametros!$B$3,IF(G51="Mágico",Parametros!$B$4,Parametros!$B$2)) -> 0.15 | K51: =IF(H51="Sim",I51*(1+J51),0) -> 0 | L51: Manter com o grupo / confirmar antes de vender.
A52: Troll | B52: 3 anéis | C52: 1 | D52: 15 | F52: Valor anotado (lote) | G52: Joia | H52: Sim | I52: =IF(D52<>"",D52,IF(E52<>"",E52,0)) -> 15 | J52: =IF(G52="Joia",Parametros!$B$3,IF(G52="Mágico",Parametros!$B$4,Parametros!$B$2)) -> 0.05 | K52: =IF(H52="Sim",I52*(1+J52),0) -> 15.75
A53: Troll | B53: Amuleto de prata de Achardalon | C53: 1 | D53: 15 | F53: Valor anotado; relevância histórica | G53: Item de missão | H53: Sim | I53: =IF(D53<>"",D53,IF(E53<>"",E53,0)) -> 15 | J53: =IF(G53="Joia",Parametros!$B$3,IF(G53="Mágico",Parametros!$B$4,Parametros!$B$2)) -> 0.15 | K53: =IF(H53="Sim",I53*(1+J53),0) -> 17.25 | L53: Manter com o grupo / confirmar antes de vender.
A54: Troll | B54: Scroll: Command | C54: 1 | E54: 50 | F54: Pergaminho mágico nível 1; estimativa | G54: Mágico | H54: Não | I54: =IF(D54<>"",D54,IF(E54<>"",E54,0)) -> 50 | J54: =IF(G54="Joia",Parametros!$B$3,IF(G54="Mágico",Parametros!$B$4,Parametros!$B$2)) -> 0.15 | K54: =IF(H54="Sim",I54*(1+J54),0) -> 0 | L54: Manter com o grupo / confirmar antes de vender.
A55: Troll | B55: Scroll: Cure Wounds nível 2 | C55: 1 | E55: 100 | F55: Pergaminho mágico nível 2; estimativa | G55: Mágico | H55: Não | I55: =IF(D55<>"",D55,IF(E55<>"",E55,0)) -> 100 | J55: =IF(G55="Joia",Parametros!$B$3,IF(G55="Mágico",Parametros!$B$4,Parametros!$B$2)) -> 0.15 | K55: =IF(H55="Sim",I55*(1+J55),0) -> 0 | L55: Manter com o grupo / confirmar antes de vender.
A56: Troll | B56: Scroll: Inflict Wounds nível 2 | C56: 1 | E56: 100 | F56: Pergaminho mágico nível 2; estimativa | G56: Mágico | H56: Não | I56: =IF(D56<>"",D56,IF(E56<>"",E56,0)) -> 100 | J56: =IF(G56="Joia",Parametros!$B$3,IF(G56="Mágico",Parametros!$B$4,Parametros!$B$2)) -> 0.15 | K56: =IF(H56="Sim",I56*(1+J56),0) -> 0 | L56: Manter com o grupo / confirmar antes de vender.
A57: Troll | B57: Scroll: Guiding Bolt nível 2 | C57: 1 | E57: 100 | F57: Pergaminho mágico nível 2; estimativa | G57: Mágico | H57: Não | I57: =IF(D57<>"",D57,IF(E57<>"",E57,0)) -> 100 | J57: =IF(G57="Joia",Parametros!$B$3,IF(G57="Mágico",Parametros!$B$4,Parametros!$B$2)) -> 0.15 | K57: =IF(H57="Sim",I57*(1+J57),0) -> 0 | L57: Manter com o grupo / confirmar antes de vender.
A58: Sala da caldeira | B58: 5 safiras | C58: 1 | D58: 50 | F58: 5 × 10 gp anotados | G58: Joia | H58: Sim | I58: =IF(D58<>"",D58,IF(E58<>"",E58,0)) -> 50 | J58: =IF(G58="Joia",Parametros!$B$3,IF(G58="Mágico",Parametros!$B$4,Parametros!$B$2)) -> 0.05 | K58: =IF(H58="Sim",I58*(1+J58),0) -> 52.5
A59: Sala da caldeira | B59: Ferro (1 kg) | C59: 1 | E59: 0.2 | F59: Ferro bruto estimado: 0,1 gp/lb | G59: Item comum | H59: Sim | I59: =IF(D59<>"",D59,IF(E59<>"",E59,0)) -> 0.2 | J59: =IF(G59="Joia",Parametros!$B$3,IF(G59="Mágico",Parametros!$B$4,Parametros!$B$2)) -> 0.15 | K59: =IF(H59="Sim",I59*(1+J59),0) -> 0.23
A60: Goblins com buraco | B60: Moedas: 231 gp | C60: 1 | D60: 231 | F60: Valor anotado | G60: Moedas | H60: Não | I60: =IF(D60<>"",D60,IF(E60<>"",E60,0)) -> 231 | J60: =IF(G60="Joia",Parametros!$B$3,IF(G60="Mágico",Parametros!$B$4,Parametros!$B$2)) -> 0.15 | K60: =IF(H60="Sim",I60*(1+J60),0) -> 0
A61: Goblins com buraco | B61: Anel de Talgen | C61: 1 | E61: 25 | F61: Pertence a Talgen; não vender | G61: Item de missão | H61: Não | I61: =IF(D61<>"",D61,IF(E61<>"",E61,0)) -> 25 | J61: =IF(G61="Joia",Parametros!$B$3,IF(G61="Mágico",Parametros!$B$4,Parametros!$B$2)) -> 0.15 | K61: =IF(H61="Sim",I61*(1+J61),0) -> 0 | L61: Manter com o grupo / confirmar antes de vender.
A62: Goblins com buraco | B62: Chaves menores | C62: 1 | E62: 0 | F62: Chaves de dungeon; sem venda até confirmar uso | G62: Item de missão | H62: Sim | I62: =IF(D62<>"",D62,IF(E62<>"",E62,0)) -> 0 | J62: =IF(G62="Joia",Parametros!$B$3,IF(G62="Mágico",Parametros!$B$4,Parametros!$B$2)) -> 0.15 | K62: =IF(H62="Sim",I62*(1+J62),0) -> 0 | L62: Manter com o grupo / confirmar antes de vender.
A63: Goblins com buraco | B63: Brincos de prata com moonstone | C63: 1 | D63: 40 | F63: Valor anotado | G63: Joia | H63: Sim | I63: =IF(D63<>"",D63,IF(E63<>"",E63,0)) -> 40 | J63: =IF(G63="Joia",Parametros!$B$3,IF(G63="Mágico",Parametros!$B$4,Parametros!$B$2)) -> 0.05 | K63: =IF(H63="Sim",I63*(1+J63),0) -> 42
A64: Goblins com buraco | B64: Colar | C64: 1 | D64: 50 | F64: Valor anotado | G64: Joia | H64: Sim | I64: =IF(D64<>"",D64,IF(E64<>"",E64,0)) -> 50 | J64: =IF(G64="Joia",Parametros!$B$3,IF(G64="Mágico",Parametros!$B$4,Parametros!$B$2)) -> 0.05 | K64: =IF(H64="Sim",I64*(1+J64),0) -> 52.5
A65: Goblins com buraco | B65: 2 ônix | C65: 1 | D65: 60 | F65: 2 × 30 gp anotados | G65: Joia | H65: Sim | I65: =IF(D65<>"",D65,IF(E65<>"",E65,0)) -> 60 | J65: =IF(G65="Joia",Parametros!$B$3,IF(G65="Mágico",Parametros!$B$4,Parametros!$B$2)) -> 0.05 | K65: =IF(H65="Sim",I65*(1+J65),0) -> 63
A66: Goblins com buraco | B66: Scroll: Faerie Fire | C66: 1 | E66: 50 | F66: Pergaminho mágico nível 1; estimativa | G66: Mágico | H66: Não | I66: =IF(D66<>"",D66,IF(E66<>"",E66,0)) -> 50 | J66: =IF(G66="Joia",Parametros!$B$3,IF(G66="Mágico",Parametros!$B$4,Parametros!$B$2)) -> 0.15 | K66: =IF(H66="Sim",I66*(1+J66),0) -> 0 | L66: Manter com o grupo / confirmar antes de vender.
A67: Goblins com buraco | B67: Scroll: Expeditious Retreat | C67: 1 | E67: 50 | F67: Pergaminho mágico nível 1; estimativa | G67: Mágico | H67: Não | I67: =IF(D67<>"",D67,IF(E67<>"",E67,0)) -> 50 | J67: =IF(G67="Joia",Parametros!$B$3,IF(G67="Mágico",Parametros!$B$4,Parametros!$B$2)) -> 0.15 | K67: =IF(H67="Sim",I67*(1+J67),0) -> 0 | L67: Manter com o grupo / confirmar antes de vender.
A68: Goblins com buraco | B68: Cloak of Billowing | C68: 1 | E68: 50 | F68: Item mágico comum; estimativa | G68: Mágico | H68: Não | I68: =IF(D68<>"",D68,IF(E68<>"",E68,0)) -> 50 | J68: =IF(G68="Joia",Parametros!$B$3,IF(G68="Mágico",Parametros!$B$4,Parametros!$B$2)) -> 0.15 | K68: =IF(H68="Sim",I68*(1+J68),0) -> 0 | L68: Manter com o grupo / confirmar antes de vender.
A69: Sala dos goblins | B69: Adaga estilo caracol | C69: 1 | D69: 5 | F69: Valor anotado | G69: Item comum | H69: Não | I69: =IF(D69<>"",D69,IF(E69<>"",E69,0)) -> 5 | J69: =IF(G69="Joia",Parametros!$B$3,IF(G69="Mágico",Parametros!$B$4,Parametros!$B$2)) -> 0.15 | K69: =IF(H69="Sim",I69*(1+J69),0) -> 0
A70: Sala dos goblins | B70: Estátua de Agatha / Corellon Larethian | C70: 1 | D70: 30 | F70: Valor anotado | G70: Arte | H70: Sim | I70: =IF(D70<>"",D70,IF(E70<>"",E70,0)) -> 30 | J70: =IF(G70="Joia",Parametros!$B$3,IF(G70="Mágico",Parametros!$B$4,Parametros!$B$2)) -> 0.15 | K70: =IF(H70="Sim",I70*(1+J70),0) -> 34.5
A71: Sala dos goblins | B71: Camisa de cota de malha | C71: 1 | E71: 45 | F71: Preço de lista D&D 5e | G71: Equipamento | H71: Sim | I71: =IF(D71<>"",D71,IF(E71<>"",E71,0)) -> 45 | J71: =IF(G71="Joia",Parametros!$B$3,IF(G71="Mágico",Parametros!$B$4,Parametros!$B$2)) -> 0.15 | K71: =IF(H71="Sim",I71*(1+J71),0) -> 51.75 | L71: Manter com o grupo / confirmar antes de vender.
A72: Gripe, Ranho e Balsag | B72: Moedas: 54 gp | C72: 1 | D72: 54 | F72: Valor anotado | G72: Moedas | H72: Não | I72: =IF(D72<>"",D72,IF(E72<>"",E72,0)) -> 54 | J72: =IF(G72="Joia",Parametros!$B$3,IF(G72="Mágico",Parametros!$B$4,Parametros!$B$2)) -> 0.15 | K72: =IF(H72="Sim",I72*(1+J72),0) -> 0
A73: Gripe, Ranho e Balsag | B73: Moedas: 241 pp | C73: 1 | D73: 24.1 | F73: 241 pp × 0,1 gp | G73: Moedas | H73: Não | I73: =IF(D73<>"",D73,IF(E73<>"",E73,0)) -> 24.1 | J73: =IF(G73="Joia",Parametros!$B$3,IF(G73="Mágico",Parametros!$B$4,Parametros!$B$2)) -> 0.15 | K73: =IF(H73="Sim",I73*(1+J73),0) -> 0
A74: Gripe, Ranho e Balsag | B74: Morningstar | C74: 1 | E74: 15 | F74: Preço de lista D&D 5e | G74: Item comum | H74: Sim | I74: =IF(D74<>"",D74,IF(E74<>"",E74,0)) -> 15 | J74: =IF(G74="Joia",Parametros!$B$3,IF(G74="Mágico",Parametros!$B$4,Parametros!$B$2)) -> 0.15 | K74: =IF(H74="Sim",I74*(1+J74),0) -> 17.25
A75: Gripe, Ranho e Balsag | B75: 2 lanças | C75: 1 | E75: 2 | F75: 2 × 1 gp (preço de lista) | G75: Item comum | H75: Sim | I75: =IF(D75<>"",D75,IF(E75<>"",E75,0)) -> 2 | J75: =IF(G75="Joia",Parametros!$B$3,IF(G75="Mágico",Parametros!$B$4,Parametros!$B$2)) -> 0.15 | K75: =IF(H75="Sim",I75*(1+J75),0) -> 2.3
A76: Gripe, Ranho e Balsag | B76: 6 javelins | C76: 1 | E76: 3 | F76: 6 × 0,5 gp (preço de lista) | G76: Item comum | H76: Sim | I76: =IF(D76<>"",D76,IF(E76<>"",E76,0)) -> 3 | J76: =IF(G76="Joia",Parametros!$B$3,IF(G76="Mágico",Parametros!$B$4,Parametros!$B$2)) -> 0.15 | K76: =IF(H76="Sim",I76*(1+J76),0) -> 3.45
A77: Gripe, Ranho e Balsag | B77: Longsword | C77: 1 | E77: 15 | F77: Preço de lista D&D 5e | G77: Item comum | H77: Sim | I77: =IF(D77<>"",D77,IF(E77<>"",E77,0)) -> 15 | J77: =IF(G77="Joia",Parametros!$B$3,IF(G77="Mágico",Parametros!$B$4,Parametros!$B$2)) -> 0.15 | K77: =IF(H77="Sim",I77*(1+J77),0) -> 17.25
A78: Gripe, Ranho e Balsag | B78: Greatsword | C78: 1 | E78: 50 | F78: Preço de lista D&D 5e | G78: Item comum | H78: Sim | I78: =IF(D78<>"",D78,IF(E78<>"",E78,0)) -> 50 | J78: =IF(G78="Joia",Parametros!$B$3,IF(G78="Mágico",Parametros!$B$4,Parametros!$B$2)) -> 0.15 | K78: =IF(H78="Sim",I78*(1+J78),0) -> 57.5
A79: Sala roxa | B79: 40 flechas | C79: 1 | E79: 2 | F79: 40 × 0,05 gp (preço de lista) | G79: Equipamento | H79: Não | I79: =IF(D79<>"",D79,IF(E79<>"",E79,0)) -> 2 | J79: =IF(G79="Joia",Parametros!$B$3,IF(G79="Mágico",Parametros!$B$4,Parametros!$B$2)) -> 0.15 | K79: =IF(H79="Sim",I79*(1+J79),0) -> 0 | L79: Manter com o grupo / confirmar antes de vender.
A80: Sala roxa | B80: Cogumelo roxo brilhante | C80: 1 | E80: 5 | F80: Consumível/curiosidade; valor muito incerto | G80: Especial | H80: Não | I80: =IF(D80<>"",D80,IF(E80<>"",E80,0)) -> 5 | J80: =IF(G80="Joia",Parametros!$B$3,IF(G80="Mágico",Parametros!$B$4,Parametros!$B$2)) -> 0.15 | K80: =IF(H80="Sim",I80*(1+J80),0) -> 0 | L80: Manter com o grupo / confirmar antes de vender.
A81: Bugbear | B81: Glaive / foice | C81: 1 | E81: 20 | F81: Preço de lista D&D 5e | G81: Item comum | H81: Sim | I81: =IF(D81<>"",D81,IF(E81<>"",E81,0)) -> 20 | J81: =IF(G81="Joia",Parametros!$B$3,IF(G81="Mágico",Parametros!$B$4,Parametros!$B$2)) -> 0.15 | K81: =IF(H81="Sim",I81*(1+J81),0) -> 23
A82: Dragão vermelho (Achardalon) | B82: Moedas: 34 gp | C82: 1 | D82: 34 | F82: Valor anotado | G82: Moedas | H82: Não | I82: =IF(D82<>"",D82,IF(E82<>"",E82,0)) -> 34 | J82: =IF(G82="Joia",Parametros!$B$3,IF(G82="Mágico",Parametros!$B$4,Parametros!$B$2)) -> 0.15 | K82: =IF(H82="Sim",I82*(1+J82),0) -> 0
A83: Dragão vermelho (Achardalon) | B83: 2 frascos de Alchemist's Fire | C83: 1 | E83: 100 | F83: 2 × 50 gp (preço de lista) | G83: Consumível | H83: Não | I83: =IF(D83<>"",D83,IF(E83<>"",E83,0)) -> 100 | J83: =IF(G83="Joia",Parametros!$B$3,IF(G83="Mágico",Parametros!$B$4,Parametros!$B$2)) -> 0.15 | K83: =IF(H83="Sim",I83*(1+J83),0) -> 0 | L83: Manter com o grupo / confirmar antes de vender.
A84: Livraria | B84: Scroll: Melf's Acid Arrow | C84: 1 | E84: 100 | F84: Pergaminho mágico nível 2; estimativa | G84: Mágico | H84: Não | I84: =IF(D84<>"",D84,IF(E84<>"",E84,0)) -> 100 | J84: =IF(G84="Joia",Parametros!$B$3,IF(G84="Mágico",Parametros!$B$4,Parametros!$B$2)) -> 0.15 | K84: =IF(H84="Sim",I84*(1+J84),0) -> 0 | L84: Manter com o grupo / confirmar antes de vender.
A85: Livraria | B85: Scroll: Scorching Ray | C85: 1 | E85: 100 | F85: Pergaminho mágico nível 2; estimativa | G85: Mágico | H85: Não | I85: =IF(D85<>"",D85,IF(E85<>"",E85,0)) -> 100 | J85: =IF(G85="Joia",Parametros!$B$3,IF(G85="Mágico",Parametros!$B$4,Parametros!$B$2)) -> 0.15 | K85: =IF(H85="Sim",I85*(1+J85),0) -> 0 | L85: Manter com o grupo / confirmar antes de vender.
A86: Livraria | B86: Livro com escamas de dragão | C86: 1 | D86: 150 | F86: Valor anotado | G86: Arte | H86: Sim | I86: =IF(D86<>"",D86,IF(E86<>"",E86,0)) -> 150 | J86: =IF(G86="Joia",Parametros!$B$3,IF(G86="Mágico",Parametros!$B$4,Parametros!$B$2)) -> 0.15 | K86: =IF(H86="Sim",I86*(1+J86),0) -> 172.5
A87: Sala de interrogatório | B87: Moedas: 365 gp | C87: 1 | D87: 365 | F87: Valor anotado | G87: Moedas | H87: Não | I87: =IF(D87<>"",D87,IF(E87<>"",E87,0)) -> 365 | J87: =IF(G87="Joia",Parametros!$B$3,IF(G87="Mágico",Parametros!$B$4,Parametros!$B$2)) -> 0.15 | K87: =IF(H87="Sim",I87*(1+J87),0) -> 0
A88: Sala de interrogatório | B88: Livro sobre vida e morte | C88: 1 | D88: 150 | F88: Valor anotado | G88: Arte | H88: Sim | I88: =IF(D88<>"",D88,IF(E88<>"",E88,0)) -> 150 | J88: =IF(G88="Joia",Parametros!$B$3,IF(G88="Mágico",Parametros!$B$4,Parametros!$B$2)) -> 0.15 | K88: =IF(H88="Sim",I88*(1+J88),0) -> 172.5
A89: Belak / Árvore Gulthias | B89: Moedas: 110 gp | C89: 1 | D89: 110 | F89: Valor anotado | G89: Moedas | H89: Não | I89: =IF(D89<>"",D89,IF(E89<>"",E89,0)) -> 110 | J89: =IF(G89="Joia",Parametros!$B$3,IF(G89="Mágico",Parametros!$B$4,Parametros!$B$2)) -> 0.15 | K89: =IF(H89="Sim",I89*(1+J89),0) -> 0
A90: Belak / Árvore Gulthias | B90: Wand of Entanglement (7 cargas) | C90: 1 | E90: 500 | F90: Item mágico incomum; estimativa de referência | G90: Mágico | H90: Não | I90: =IF(D90<>"",D90,IF(E90<>"",E90,0)) -> 500 | J90: =IF(G90="Joia",Parametros!$B$3,IF(G90="Mágico",Parametros!$B$4,Parametros!$B$2)) -> 0.15 | K90: =IF(H90="Sim",I90*(1+J90),0) -> 0 | L90: Manter com o grupo / confirmar antes de vender.
A91: Belak / Árvore Gulthias | B91: Diversas chaves | C91: 1 | E91: 0 | F91: Chaves do andar; sem venda até confirmar uso | G91: Item de missão | H91: Sim | I91: =IF(D91<>"",D91,IF(E91<>"",E91,0)) -> 0 | J91: =IF(G91="Joia",Parametros!$B$3,IF(G91="Mágico",Parametros!$B$4,Parametros!$B$2)) -> 0.15 | K91: =IF(H91="Sim",I91*(1+J91),0) -> 0 | L91: Manter com o grupo / confirmar antes de vender.
A92: Belak / Árvore Gulthias | B92: Chave ornamentada de dragão | C92: 1 | E92: 50 | F92: Possível chave importante; estimativa meramente indicativa | G92: Item de missão | H92: Sim | I92: =IF(D92<>"",D92,IF(E92<>"",E92,0)) -> 50 | J92: =IF(G92="Joia",Parametros!$B$3,IF(G92="Mágico",Parametros!$B$4,Parametros!$B$2)) -> 0.15 | K92: =IF(H92="Sim",I92*(1+J92),0) -> 57.5 | L92: Manter com o grupo / confirmar antes de vender.
A93: Belak / Árvore Gulthias | B93: Diamante para Revivify | C93: 1 | E93: 300 | F93: Custo material padrão de Revivify; confirmar valor | G93: Joia | H93: Não | I93: =IF(D93<>"",D93,IF(E93<>"",E93,0)) -> 300 | J93: =IF(G93="Joia",Parametros!$B$3,IF(G93="Mágico",Parametros!$B$4,Parametros!$B$2)) -> 0.05 | K93: =IF(H93="Sim",I93*(1+J93),0) -> 0
A94: Belak / Árvore Gulthias | B94: Shatterspike (espada mágica de Sir Bradford) | C94: 1 | E94: 1000 | F94: Arma mágica +1; pertence a Sir Bradford | G94: Item de missão | H94: Não | I94: =IF(D94<>"",D94,IF(E94<>"",E94,0)) -> 1000 | J94: =IF(G94="Joia",Parametros!$B$3,IF(G94="Mágico",Parametros!$B$4,Parametros!$B$2)) -> 0.15 | K94: =IF(H94="Sim",I94*(1+J94),0) -> 0 | L94: Manter com o grupo / confirmar antes de vender.
A95: Belak / Árvore Gulthias | B95: 3 poções de Healing | C95: 1 | E95: 150 | F95: 3 × 50 gp (estimativa) | G95: Mágico | H95: Não | I95: =IF(D95<>"",D95,IF(E95<>"",E95,0)) -> 150 | J95: =IF(G95="Joia",Parametros!$B$3,IF(G95="Mágico",Parametros!$B$4,Parametros!$B$2)) -> 0.15 | K95: =IF(H95="Sim",I95*(1+J95),0) -> 0 | L95: Manter com o grupo / confirmar antes de vender.
A96: Belak / Árvore Gulthias | B96: 2 poções de Antitoxina | C96: 1 | E96: 100 | F96: 2 × 50 gp (estimativa) | G96: Consumível | H96: Não | I96: =IF(D96<>"",D96,IF(E96<>"",E96,0)) -> 100 | J96: =IF(G96="Joia",Parametros!$B$3,IF(G96="Mágico",Parametros!$B$4,Parametros!$B$2)) -> 0.15 | K96: =IF(H96="Sim",I96*(1+J96),0) -> 0 | L96: Manter com o grupo / confirmar antes de vender.
A97: Sala do capiroto | B97: 2 safiras | C97: 1 | D97: 100 | F97: 2 × 50 gp anotados | G97: Joia | H97: Sim | I97: =IF(D97<>"",D97,IF(E97<>"",E97,0)) -> 100 | J97: =IF(G97="Joia",Parametros!$B$3,IF(G97="Mágico",Parametros!$B$4,Parametros!$B$2)) -> 0.05 | K97: =IF(H97="Sim",I97*(1+J97),0) -> 105
A98: Carolyn Ukrele | B98: Recompensa Carolyn | C98: 1 | D98: 1500 | F98: 500 gp + 1.000 gp anotados | G98: Recompensa | H98: Não | I98: =IF(D98<>"",D98,IF(E98<>"",E98,0)) -> 1500 | J98: =IF(G98="Joia",Parametros!$B$3,IF(G98="Mágico",Parametros!$B$4,Parametros!$B$2)) -> 0.15 | K98: =IF(H98="Sim",I98*(1+J98),0) -> 0

Sheet Resumo
A1: Resumo do caixa e divisão — Amigos do Zé Colmeia
A3: Componente | B3: Total (gp)
A4: Moedas e recompensas em caixa | B4: =SUM(Calculos!D2:D104) -> 2604.6
A5: Receita estimada de vendas | B5: =SUM(Calculos!E2:E104) -> 1771.0365
A6: Total disponível para dividir | B6: =B4+B5 -> 4375.6365
A7: Divisão por pessoa | B7: =B6/Parametros!$B$5 -> 1458.5455
A8: Itens mantidos (valor de referência) | B8: =SUM(Calculos!F2:F104) -> 5623
A10: Personagem | B10: Parte igual (gp)
A11: Karstaag | B11: =$B$7 -> 1458.5455
A12: Thorbir | B12: =$B$7 -> 1458.5455
A13: Mercival | B13: =$B$7 -> 1458.5455
A15: Notas
A16: • Itens marcados como “Não” não entram na venda nem na divisão de caixa.
A17: • Moedas e recompensa entram integralmente no caixa; não recebem bônus de venda.
A18: • Bônus aplicados: 15% comuns, 5% joias/arte e 15% mágicos (caso a decisão seja alterada).
A19: • Valores “estimados” são referência de mesa e devem ser ajustados ao avaliar com comerciante/Mestre.

Sheet Parâmetros
A1: Parâmetro | B1: Valor
A2: Bônus de venda — itens comuns | B2: 0.15
A3: Bônus de venda — gemas/arte | B3: 0.05
A4: Bônus de venda — itens mágicos | B4: 0.15
A5: Divisores (membros) | B5: 3

Sheet Parametros
A1: Parâmetro | B1: Valor
A2: Bônus de venda — itens comuns | B2: 0.15
A3: Bônus de venda — gemas/arte | B3: 0.05
A4: Bônus de venda — itens mágicos | B4: 0.15
A5: Divisores (membros) | B5: 3

Sheet Calculos
A1: Categoria | B1: Vender? | C1: Base | D1: Caixa | E1: Venda | F1: Mantido
A2: Item comum | B2: Sim | C2: 25 | D2: 0 | E2: 28.75 | F2: 0
A3: Item comum | B3: Sim | C3: 10 | D3: 0 | E3: 11.5 | F3: 0
A4: Moedas | B4: Não | C4: 4.3 | D4: 4.3 | E4: 0 | F4: 0
A5: Moedas | B5: Não | C5: 9 | D5: 9 | E5: 0 | F5: 0
A6: Mágico | B6: Não | C6: 150 | D6: 0 | E6: 0 | F6: 150
A7: Especial | B7: Não | C7: 25 | D7: 0 | E7: 0 | F7: 25
A8: Item comum | B8: Sim | C8: 5 | D8: 0 | E8: 5.75 | F8: 0
A9: Item comum | B9: Sim | C9: 12.5 | D9: 0 | E9: 14.375 | F9: 0
A10: Item comum | B10: Sim | C10: 0.8 | D10: 0 | E10: 0.92 | F10: 0
A11: Mágico | B11: Não | C11: 500 | D11: 0 | E11: 0 | F11: 500
A12: Mágico | B12: Não | C12: 300 | D12: 0 | E12: 0 | F12: 300
A13: Mágico | B13: Não | C13: 150 | D13: 0 | E13: 0 | F13: 150
... A104: Recompensa | B104: Não | C104: 1500 | D104: 1500 | E104: 0 | F104: 0
